pydagmc/__init__.py
pydagmc/dagnav.py
pydagmc-0.0.1.dist-info/licenses/LICENSE
pydagmc-0.0.1.dist-info/METADATA
pydagmc-0.0.1.dist-info/WHEEL
pydagmc-0.0.1.dist-info/top_level.txt
pydagmc-0.0.1.dist-info/RECORD
