Metadata-Version: 2.4
Name: pydagmc
Version: 0.0.1
Summary: A convenience interface for examining,
Author-email: Patrick Shriwise <pshriwise@gmail.com>, Paul Wilson <paul.wilson@wisc.edu>, Paul Romano <paul.k.romano@gmail.com>, Ethan Peterson <ethan.peterson@mit.edu>, Ahnaf Tahmid Chowdhury <tahmid@nukehub.org>, Jonathan Shimwell <drshimwell@gmail.com>
License: MIT
Project-URL: Bug Tracker, https://github.com/svalinn/pydagmc/issues
Project-URL: Source Code, https://github.com/svalinn/pydagmc
Classifier: Development Status :: 4 - Beta
Classifier: Intended Audience :: Developers
Classifier: Intended Audience :: End Users/Desktop
Classifier: Intended Audience :: Science/Research
Classifier: License :: OSI Approved :: MIT License
Classifier: Natural Language :: English
Classifier: Operating System :: OS Independent
Classifier: Topic :: Scientific/Engineering
Classifier: Programming Language :: Python :: 3
Requires-Python: >=3.8
License-File: LICENSE
Requires-Dist: numpy
Provides-Extra: test
Requires-Dist: pytest; extra == "test"
Provides-Extra: ci
Requires-Dist: pytest-cov; extra == "ci"
Dynamic: license-file
